remotePy/__init__.py
remotePy/client/__init__.py
remotePy/client/CSharp/__init__.py
remotePy/client/JavaScript/__init__.py
remotePy/client/Python/__init__.py
remotePy/server/__init__.py
remotepy-0.0.0.dist-info/LICENSE
remotepy-0.0.0.dist-info/METADATA
remotepy-0.0.0.dist-info/WHEEL
remotepy-0.0.0.dist-info/top_level.txt
remotepy-0.0.0.dist-info/RECORD
