Metadata-Version: 2.1
Name: remotepy
Version: 0.0.0
Summary: remote Py allows Python functions to be called remotely from multiple languages including JavaScript, CSharp and Python
Home-page: https://www.remotePy.com
Author: Farukh Dilawar Tamboli
Author-email: farukht@gmail.com
License: UNKNOWN
Platform: UNKNOWN
Classifier: Programming Language :: Python :: 3
Classifier: License :: OSI Approved :: GNU General Public License v3 (GPLv3)
Classifier: Operating System :: OS Independent
